queryones/__init__.py
queryones/data.db
queryones/main.py
queryones-0.1.2.dist-info/WHEEL
queryones-0.1.2.dist-info/METADATA
queryones-0.1.2.dist-info/RECORD
