Metadata-Version: 2.1
Name: queryones
Version: 0.1.2
Summary: Executing multiple sqlite queries
Home-page: https://github.com/nixonsis/query_ones
Author: to101
Author-email: to101kv@gmail.com
Requires-Python: >=3.1,<4.0
Classifier: Programming Language :: Python :: 3
Classifier: Programming Language :: Python :: 3.10
Classifier: Programming Language :: Python :: 3.4
Classifier: Programming Language :: Python :: 3.5
Classifier: Programming Language :: Python :: 3.6
Classifier: Programming Language :: Python :: 3.7
Classifier: Programming Language :: Python :: 3.8
Classifier: Programming Language :: Python :: 3.9
Project-URL: Repository, https://github.com/nixonsis/query_ones
